.gitignore
.gitlab-ci.yml
LICENSE
README.md
TODO.org
pyproject.toml
./pipelet3/__init__.py
./pipelet3/cli.py
./pipelet3/external_events.py
./pipelet3/processing_graph.py
./pipelet3/rpc.py
./pipelet3/scheduler.py
./pipelet3/socketrpc.py
./pipelet3/worker.py
./stardiceonline/__init__.py
./stardiceonline/_version.py
./stardiceonline.egg-info/PKG-INFO
./stardiceonline.egg-info/SOURCES.txt
./stardiceonline.egg-info/dependency_links.txt
./stardiceonline.egg-info/entry_points.txt
./stardiceonline.egg-info/requires.txt
./stardiceonline.egg-info/top_level.txt
./stardiceonline/archive/__init__.py
./stardiceonline/archive/archive.py
./stardiceonline/archive/file_tools.py
./stardiceonline/archive/file_watcher.py
./stardiceonline/archive/ssh.py
./stardiceonline/processing/__init__.py
./stardiceonline/processing/astrometric_model.py
./stardiceonline/processing/astrometry.py
./stardiceonline/processing/catalog.py
./stardiceonline/processing/ctoolbox.py
./stardiceonline/processing/deblend.py
./stardiceonline/processing/detrending.py
./stardiceonline/processing/forced_photometry.py
./stardiceonline/processing/gaussfit.py
./stardiceonline/processing/image.py
./stardiceonline/processing/jaxfitter.py
./stardiceonline/processing/led_photometry.py
./stardiceonline/processing/minimap.py
./stardiceonline/processing/photometry.py
./stardiceonline/processing/pipeline.py
./stardiceonline/processing/processor.py
./stardiceonline/processing/read_headers.py
./stardiceonline/processing/reference_catalog.py
./stardiceonline/processing/robuststat.py
./stardiceonline/processing/sphere_photometry.py
./stardiceonline/simulation/fakecomponents.py
./stardiceonline/simulation/fakeinstrument.py
./stardiceonline/simulation/gaia.py
./stardiceonline/tools/__init__.py
./stardiceonline/tools/command_line.py
./stardiceonline/tools/config.py
./stardiceonline/tools/datesandtimes.py
./stardiceonline/tools/main.py
./stardiceonline/tools/match.py
./stardiceonline/tools/metadatamanager.py
./stardiceonline/tools/orgfiles.py
./stardiceonline/web/L_visibility.py
./stardiceonline/web/__init__.py
./stardiceonline/web/directories.py
./stardiceonline/web/fancywebcam_server.py
./stardiceonline/web/image_selection_widget.py
./stardiceonline/web/logger_widget.py
stardiceonline.egg-info/SOURCES.txt
