Metadata-Version: 2.1
Name: stardiceonline
Version: 0.1.3
Summary: Data reduction chain for the StarDICE experiment
Author-email: Marc Betoule <marc.betoule@lpnhe.in2p3.fr>, Sébastien Bongard <sebastien.bongard@lpnhe.in2p3.fr>, Jérémy Neveu <jeremy.neveu@lpnhe.in2p3.fr>, Thierry Souverin <thierry.souverin@lpnhe.in2p3.fr>
Project-URL: Homepage, https://gitlab.in2p3.fr/stardice/stardiceonline
Project-URL: Bug Tracker, https://gitlab.in2p3.fr/stardice/stardiceonline/-/issues
Classifier: Programming Language :: Python :: 3
Classifier: License :: OSI Approved :: GNU General Public License v2 (GPLv2)
Classifier: Operating System :: OS Independent
Requires-Python: >=3.7
License-File: LICENSE
Requires-Dist: platformdirs
Requires-Dist: argparse
Requires-Dist: argcomplete
Requires-Dist: ssh_agent_setup
Requires-Dist: bokeh<3.4
Requires-Dist: astropy
Requires-Dist: watchdog
Requires-Dist: tqdm
Requires-Dist: requests
Requires-Dist: scipy
Requires-Dist: jax[cpu]
Requires-Dist: getcalspec
Requires-Dist: psutil
Requires-Dist: skyfield
Requires-Dist: bcrypt
Requires-Dist: pytest
Requires-Dist: pytest-cov
